dropit/__init__.py
dropit/main.py
dropit/static/scripts.js
dropit/static/styles.css
dropit/templates/index.html
dropit-0.1.10.dist-info/LICENSE
dropit-0.1.10.dist-info/METADATA
dropit-0.1.10.dist-info/WHEEL
dropit-0.1.10.dist-info/entry_points.txt
dropit-0.1.10.dist-info/top_level.txt
dropit-0.1.10.dist-info/RECORD
