Metadata-Version: 2.1
Name: dropit
Version: 0.1.10
Summary: A Flask-based command line file sharing application.
Home-page: https://github.com/1darshanpatil/dropit
Author: Darshan P.
Author-email: drshnp@outlook.com
Classifier: Development Status :: 3 - Alpha
Classifier: Intended Audience :: Developers
Classifier: License :: OSI Approved :: MIT License
Classifier: Programming Language :: Python :: 3
Classifier: Programming Language :: Python :: 3.7
Classifier: Programming Language :: Python :: 3.8
Classifier: Programming Language :: Python :: 3.9
Classifier: Framework :: Flask
Requires-Python: >=3.6
License-File: LICENSE
Requires-Dist: Flask==3.0.3
Requires-Dist: Flask-BasicAuth==0.2.0
Requires-Dist: qrcode==7.4.2
Requires-Dist: click<8.2.0,>=8.0.0
Requires-Dist: Werkzeug==3.1.3
Requires-Dist: Jinja2==3.1.6
Requires-Dist: MarkupSafe==3.0.2
Requires-Dist: itsdangerous==2.2.0
Requires-Dist: typing-extensions==4.14.1
Requires-Dist: blinker==1.9.0
Requires-Dist: cryptography==45.0.5
Requires-Dist: cffi==1.17.1
Requires-Dist: pycparser==2.22
Requires-Dist: pypng==0.20220715.0
